xk/ChangYing.py
xk/__init__.py
xk/sqlite.py
xk_python-25.3.26.10.38.dist-info/licenses/LICENSE
xk_python-25.3.26.10.38.dist-info/METADATA
xk_python-25.3.26.10.38.dist-info/WHEEL
xk_python-25.3.26.10.38.dist-info/top_level.txt
xk_python-25.3.26.10.38.dist-info/RECORD
